openoracle/__init__.py
openoracle/ai/__init__.py
openoracle/ai/pure_ai_router.py
openoracle/ai/pure_ai_routing.py
openoracle/api/__init__.py
openoracle/api/client.py
openoracle/api/market_endpoints.py
openoracle/core/client.py
openoracle/core/config.py
openoracle/core/exceptions.py
openoracle/core/router.py
openoracle/database/supabase_client.py
openoracle/schemas/contract_json_schemas.py
openoracle/schemas/contract_schemas.py
openoracle/schemas/oracle_schemas.py
openoracle/schemas/prediction_market_schemas.py
openoracle/services/interactive_market_service.py
openoracle/services/market_creation_service.py
openoracle/services/market_optimizer_service.py
openoracle/services/proxy_client.py
openoracle/services/secure_ai_router.py
openoracle/services/walrus_storage.py
openoracle/utils/__init__.py
openoracle/utils/async_helpers.py
openoracle/utils/cache.py
openoracle/utils/logger.py
openoracle/utils/retry.py
openoracle-1.0.0.dist-info/LICENSE
openoracle-1.0.0.dist-info/METADATA
openoracle-1.0.0.dist-info/WHEEL
openoracle-1.0.0.dist-info/entry_points.txt
openoracle-1.0.0.dist-info/top_level.txt
openoracle-1.0.0.dist-info/RECORD
