Metadata-Version: 2.1
Name: openoracle
Version: 1.0.0
Summary: Intelligent Oracle Routing for Prediction Markets
Home-page: https://github.com/openoracle/python-sdk
Author: OpenOracle Team
Author-email: OpenOracle Team <team@openoracle.ai>
License: MIT
Project-URL: Homepage, https://openoracle.ai
Project-URL: Documentation, https://docs.openoracle.ai
Project-URL: Repository, https://github.com/openoracle/python-sdk
Project-URL: Issues, https://github.com/openoracle/python-sdk/issues
Keywords: oracle,blockchain,prediction-markets,defi,chainlink,pyth,uma,api3,band-protocol,ai,routing,twitter,social-media
Classifier: Development Status :: 3 - Alpha
Classifier: Intended Audience :: Developers
Classifier: License :: OSI Approved :: MIT License
Classifier: Operating System :: OS Independent
Classifier: Programming Language :: Python :: 3
Classifier: Programming Language :: Python :: 3.9
Classifier: Programming Language :: Python :: 3.10
Classifier: Programming Language :: Python :: 3.11
Classifier: Programming Language :: Python :: 3.12
Classifier: Topic :: Software Development :: Libraries :: Python Modules
Classifier: Topic :: Internet :: WWW/HTTP :: Dynamic Content
Classifier: Topic :: Scientific/Engineering :: Artificial Intelligence
Requires-Python: >=3.9
License-File: LICENSE
Requires-Dist: aiohttp >=3.8.0
Requires-Dist: pydantic >=2.0.0
Requires-Dist: python-dotenv >=1.0.0
Requires-Dist: web3 >=6.0.0
Requires-Dist: python-dateutil >=2.8.0
Requires-Dist: tenacity >=8.0.0
Requires-Dist: cachetools >=5.0.0
Requires-Dist: cryptography >=41.0.0
Requires-Dist: PyJWT >=2.8.0
Requires-Dist: websockets >=11.0.0
Provides-Extra: all
Requires-Dist: jupyter >=1.0.0 ; extra == 'all'
Requires-Dist: pandas >=2.0.0 ; extra == 'all'
Requires-Dist: plotly >=5.0.0 ; extra == 'all'
Requires-Dist: streamlit >=1.28.0 ; extra == 'all'
Provides-Extra: dev
Requires-Dist: pytest >=7.0.0 ; extra == 'dev'
Requires-Dist: pytest-asyncio >=0.21.0 ; extra == 'dev'
Requires-Dist: pytest-cov >=4.0.0 ; extra == 'dev'
Requires-Dist: black >=23.0.0 ; extra == 'dev'
Requires-Dist: isort >=5.12.0 ; extra == 'dev'
Requires-Dist: flake8 >=6.0.0 ; extra == 'dev'
Requires-Dist: mypy >=1.0.0 ; extra == 'dev'
Requires-Dist: pre-commit >=3.0.0 ; extra == 'dev'
Provides-Extra: docs
Requires-Dist: sphinx >=6.0.0 ; extra == 'docs'
Requires-Dist: sphinx-rtd-theme >=1.2.0 ; extra == 'docs'
Requires-Dist: myst-parser >=1.0.0 ; extra == 'docs'
